[
  {
    "hex": "0x0",
    "name": "SO_PROTO_REGISTER",
    "source": "SharedIP/SIP-NKE.kmodproj/SharedIP.h",
    "type": "PreprocessorConstant"
  },
  {
    "hex": "0x0",
    "name": "SO_PORT_RESERVE",
    "source": "SharedIP/SIP-NKE.kmodproj/SharedIP.h",
    "type": "PreprocessorConstant"
  },
  {
    "hex": "0x0",
    "name": "SO_PORT_RELEASE",
    "source": "SharedIP/SIP-NKE.kmodproj/SharedIP.h",
    "type": "PreprocessorConstant"
  },
  {
    "hex": "0x0",
    "name": "SO_PORT_LOOKUP",
    "source": "SharedIP/SIP-NKE.kmodproj/SharedIP.h",
    "type": "PreprocessorConstant"
  },
  {
    "hex": "0x0",
    "name": "SIP_PROTO_ATALK",
    "source": "SharedIP/SIP-NKE.kmodproj/SharedIP.h",
    "type": "PreprocessorConstant"
  },
  {
    "hex": "0x0",
    "name": "SIP_PROTO_IPv4",
    "source": "SharedIP/SIP-NKE.kmodproj/SharedIP.h",
    "type": "PreprocessorConstant"
  },
  {
    "hex": "0x0",
    "name": "SIP_PROTO_RCV_ALL",
    "source": "SharedIP/SIP-NKE.kmodproj/SharedIP.h",
    "type": "PreprocessorConstant"
  },
  {
    "hex": "0x0",
    "name": "SIP_PROTO_RCV_FILT",
    "source": "SharedIP/SIP-NKE.kmodproj/SharedIP.h",
    "type": "PreprocessorConstant"
  },
  {
    "hex": "0x0",
    "name": "SIP_PROTO_RCV_SHARED",
    "source": "SharedIP/SIP-NKE.kmodproj/SharedIP.h",
    "type": "PreprocessorConstant"
  },
  {
    "hex": "0x0",
    "name": "SIP_PROTO_ENABLE",
    "source": "SharedIP/SIP-NKE.kmodproj/SharedIP.h",
    "type": "PreprocessorConstant"
  },
  {
    "hex": "0x0",
    "name": "SIP_PROTO_DISABLE",
    "source": "SharedIP/SIP-NKE.kmodproj/SharedIP.h",
    "type": "PreprocessorConstant"
  },
  {
    "hex": "0x0",
    "name": "si_initted",
    "source": "SharedIP/SIP-NKE.kmodproj/sip.c",
    "type": "EnumCase"
  },
  {
    "hex": "0x0",
    "name": "sip_mtx",
    "source": "SharedIP/SIP-NKE.kmodproj/sip.c",
    "type": "EnumCase"
  },
  {
    "hex": "0x0",
    "name": "si_initted",
    "source": "SharedIP/SIP-NKE.kmodproj/sip.c",
    "type": "EnumCase"
  },
  {
    "hex": "0x0",
    "name": "size",
    "source": "SharedIP/SIP-NKE.kmodproj/sip.c",
    "type": "EnumCase"
  },
  {
    "hex": "0x0",
    "name": "error",
    "source": "SharedIP/SIP-NKE.kmodproj/sip.c",
    "type": "EnumCase"
  },
  {
    "hex": "0x20000",
    "name": "size",
    "source": "SharedIP/SIP-NKE.kmodproj/sip.c",
    "type": "EnumCase"
  },
  {
    "hex": "0x0",
    "name": "error",
    "source": "SharedIP/SIP-NKE.kmodproj/sip.c",
    "type": "EnumCase"
  },
  {
    "hex": "0x0",
    "name": "error",
    "source": "SharedIP/SIP-NKE.kmodproj/sip.c",
    "type": "EnumCase"
  },
  {
    "hex": "0x1",
    "name": "noifpnotify",
    "source": "SharedIP/SIP-NKE.kmodproj/sip.c",
    "type": "EnumCase"
  },
  {
    "hex": "0x0",
    "name": "error",
    "source": "SharedIP/SIP-NKE.kmodproj/sip.c",
    "type": "EnumCase"
  },
  {
    "hex": "0x0",
    "name": "handled",
    "source": "SharedIP/SIP-NKE.kmodproj/sip.c",
    "type": "EnumCase"
  },
  {
    "hex": "0x1",
    "name": "handled",
    "source": "SharedIP/SIP-NKE.kmodproj/sip.c",
    "type": "EnumCase"
  },
  {
    "hex": "0x0",
    "name": "so",
    "source": "SharedIP/SIP-NKE.kmodproj/sip.c",
    "type": "EnumCase"
  },
  {
    "hex": "0x1",
    "name": "handled",
    "source": "SharedIP/SIP-NKE.kmodproj/sip.c",
    "type": "EnumCase"
  },
  {
    "hex": "0x1",
    "name": "handled",
    "source": "SharedIP/SIP-NKE.kmodproj/sip.c",
    "type": "EnumCase"
  },
  {
    "hex": "0x0",
    "name": "error",
    "source": "SharedIP/SIP-NKE.kmodproj/sip.c",
    "type": "EnumCase"
  },
  {
    "hex": "0x0",
    "name": "error",
    "source": "SharedIP/SIP-NKE.kmodproj/sip.c",
    "type": "EnumCase"
  },
  {
    "hex": "0x0",
    "name": "grp_attrib",
    "source": "SharedIP/SIP-NKE.kmodproj/sip.c",
    "type": "EnumCase"
  },
  {
    "hex": "0x0",
    "name": "lck_attrib",
    "source": "SharedIP/SIP-NKE.kmodproj/sip.c",
    "type": "EnumCase"
  },
  {
    "hex": "0x1",
    "name": "si_initted",
    "source": "SharedIP/SIP-NKE.kmodproj/sip.c",
    "type": "EnumCase"
  },
  {
    "hex": "0x0",
    "name": "BF_flags",
    "source": "SharedIP/SIP-NKE.kmodproj/sip.c",
    "type": "EnumCase"
  },
  {
    "hex": "0x0",
    "name": "sip_mtx",
    "source": "SharedIP/SIP-NKE.kmodproj/sip.c",
    "type": "EnumCase"
  },
  {
    "hex": "0x0",
    "name": "sip_lock_group",
    "source": "SharedIP/SIP-NKE.kmodproj/sip.c",
    "type": "EnumCase"
  },
  {
    "hex": "0x0",
    "name": "sdl_nlen",
    "source": "SharedIP/SIP-NKE.kmodproj/sip.c",
    "type": "EnumCase"
  },
  {
    "hex": "0x6",
    "name": "sdl_alen",
    "source": "SharedIP/SIP-NKE.kmodproj/sip.c",
    "type": "EnumCase"
  },
  {
    "hex": "0x0",
    "name": "sdl_slen",
    "source": "SharedIP/SIP-NKE.kmodproj/sip.c",
    "type": "EnumCase"
  },
  {
    "hex": "0x0",
    "name": "error",
    "source": "SharedIP/SIP-NKE.kmodproj/sip.c",
    "type": "EnumCase"
  },
  {
    "hex": "0x0",
    "name": "i",
    "source": "SharedIP/SIP-NKE.kmodproj/sip.c",
    "type": "EnumCase"
  },
  {
    "hex": "0x0",
    "name": "i",
    "source": "SharedIP/SIP-NKE.kmodproj/sip.c",
    "type": "EnumCase"
  },
  {
    "hex": "0x0",
    "name": "error",
    "source": "SharedIP/SIP-NKE.kmodproj/sip.c",
    "type": "EnumCase"
  },
  {
    "hex": "0x0",
    "name": "SIP_DEBUG_FLOW",
    "source": "SharedIP/SIP-NKE.kmodproj/sip.h",
    "type": "PreprocessorConstant"
  },
  {
    "hex": "0x0",
    "name": "SIP_DEBUG",
    "source": "SharedIP/SIP-NKE.kmodproj/sip.h",
    "type": "PreprocessorConstant"
  },
  {
    "hex": "0x1",
    "name": "SIP_DEBUG_ERR",
    "source": "SharedIP/SIP-NKE.kmodproj/sip.h",
    "type": "PreprocessorConstant"
  },
  {
    "hex": "0x0",
    "name": "SIP_DEBUG_INFO",
    "source": "SharedIP/SIP-NKE.kmodproj/sip.h",
    "type": "PreprocessorConstant"
  },
  {
    "hex": "0x1",
    "name": "DEBUG_MSG",
    "source": "SharedIP/SIP-NKE.kmodproj/sip.h",
    "type": "PreprocessorConstant"
  },
  {
    "hex": "0x0",
    "name": "DO_LOG",
    "source": "SharedIP/SIP-NKE.kmodproj/sip.h",
    "type": "PreprocessorConstant"
  },
  {
    "hex": "0x0",
    "name": "SharedIP_Handle",
    "source": "SharedIP/SIP-NKE.kmodproj/sip.h",
    "type": "PreprocessorConstant"
  },
  {
    "hex": "0x1C",
    "name": "FILTER_LEN",
    "source": "SharedIP/SIP-NKE.kmodproj/sip.h",
    "type": "PreprocessorConstant"
  },
  {
    "hex": "0x0",
    "name": "BFS_ATALK",
    "source": "SharedIP/SIP-NKE.kmodproj/sip.h",
    "type": "PreprocessorConstant"
  },
  {
    "hex": "0x1",
    "name": "BFS_IP",
    "source": "SharedIP/SIP-NKE.kmodproj/sip.h",
    "type": "PreprocessorConstant"
  },
  {
    "hex": "0x2",
    "name": "BFS_COUNT",
    "source": "SharedIP/SIP-NKE.kmodproj/sip.h",
    "type": "PreprocessorConstant"
  },
  {
    "hex": "0x0",
    "name": "i",
    "source": "SharedIP/SIP-NKE.kmodproj/sip_atalk.c",
    "type": "EnumCase"
  },
  {
    "hex": "0x11",
    "name": "reqlen",
    "source": "SharedIP/SIP-NKE.kmodproj/sip_atalk.c",
    "type": "EnumCase"
  },
  {
    "hex": "0x0",
    "name": "m_orig",
    "source": "SharedIP/SIP-NKE.kmodproj/sip_atalk.c",
    "type": "EnumCase"
  },
  {
    "hex": "0x0",
    "name": "m_orig",
    "source": "SharedIP/SIP-NKE.kmodproj/sip_atalk.c",
    "type": "EnumCase"
  },
  {
    "hex": "0x0",
    "name": "retval",
    "source": "SharedIP/SIP-NKE.kmodproj/sip_atalk.c",
    "type": "EnumCase"
  },
  {
    "hex": "0x0",
    "name": "iff_protocol",
    "source": "SharedIP/SIP-NKE.kmodproj/sip_atalk.c",
    "type": "EnumCase"
  },
  {
    "hex": "0x0",
    "name": "retval",
    "source": "SharedIP/SIP-NKE.kmodproj/sip_atalk.c",
    "type": "EnumCase"
  },
  {
    "hex": "0x1",
    "name": "atalk_stopping",
    "source": "SharedIP/SIP-NKE.kmodproj/sip_atalk.c",
    "type": "EnumCase"
  },
  {
    "hex": "0x0",
    "name": "atalk_stopping",
    "source": "SharedIP/SIP-NKE.kmodproj/sip_atalk.c",
    "type": "EnumCase"
  },
  {
    "hex": "0x0",
    "name": "atalk_proto_filter",
    "source": "SharedIP/SIP-NKE.kmodproj/sip_atalk.c",
    "type": "EnumCase"
  },
  {
    "hex": "0x0",
    "name": "udp_blue_owned",
    "source": "SharedIP/SIP-NKE.kmodproj/sip_inet.c",
    "type": "EnumCase"
  },
  {
    "hex": "0x6",
    "name": "media_addr_size",
    "source": "SharedIP/SIP-NKE.kmodproj/sip_inet.c",
    "type": "EnumCase"
  },
  {
    "hex": "0x0",
    "name": "media_addr_size",
    "source": "SharedIP/SIP-NKE.kmodproj/sip_inet.c",
    "type": "EnumCase"
  },
  {
    "hex": "0x0",
    "name": "udp_blue_owned",
    "source": "SharedIP/SIP-NKE.kmodproj/sip_inet.c",
    "type": "EnumCase"
  },
  {
    "hex": "0x0",
    "name": "tcp_blue_owned",
    "source": "SharedIP/SIP-NKE.kmodproj/sip_inet.c",
    "type": "EnumCase"
  },
  {
    "hex": "0x0",
    "name": "udp_blue_owned",
    "source": "SharedIP/SIP-NKE.kmodproj/sip_inet.c",
    "type": "EnumCase"
  },
  {
    "hex": "0x0",
    "name": "tcp_blue_owned",
    "source": "SharedIP/SIP-NKE.kmodproj/sip_inet.c",
    "type": "EnumCase"
  },
  {
    "hex": "0x0",
    "name": "payload_offset",
    "source": "SharedIP/SIP-NKE.kmodproj/sip_inet.c",
    "type": "EnumCase"
  },
  {
    "hex": "0x0",
    "name": "ip_sum",
    "source": "SharedIP/SIP-NKE.kmodproj/sip_inet.c",
    "type": "EnumCase"
  },
  {
    "hex": "0x0",
    "name": "ip_sum",
    "source": "SharedIP/SIP-NKE.kmodproj/sip_inet.c",
    "type": "EnumCase"
  },
  {
    "hex": "0x0",
    "name": "error",
    "source": "SharedIP/SIP-NKE.kmodproj/sip_inet.c",
    "type": "EnumCase"
  },
  {
    "hex": "0x0",
    "name": "owner",
    "source": "SharedIP/SIP-NKE.kmodproj/sip_inet.c",
    "type": "EnumCase"
  },
  {
    "hex": "0x0",
    "name": "sum_req",
    "source": "SharedIP/SIP-NKE.kmodproj/sip_inet.c",
    "type": "EnumCase"
  },
  {
    "hex": "0x0",
    "name": "sum_value",
    "source": "SharedIP/SIP-NKE.kmodproj/sip_inet.c",
    "type": "EnumCase"
  },
  {
    "hex": "0x0",
    "name": "ip_off",
    "source": "SharedIP/SIP-NKE.kmodproj/sip_inet.c",
    "type": "EnumCase"
  },
  {
    "hex": "0x0",
    "name": "result",
    "source": "SharedIP/SIP-NKE.kmodproj/sip_inet.c",
    "type": "EnumCase"
  },
  {
    "hex": "0x0",
    "name": "error",
    "source": "SharedIP/SIP-NKE.kmodproj/sip_inet.c",
    "type": "EnumCase"
  },
  {
    "hex": "0x0",
    "name": "error",
    "source": "SharedIP/SIP-NKE.kmodproj/sip_inet.c",
    "type": "EnumCase"
  },
  {
    "hex": "0x0",
    "name": "retval",
    "source": "SharedIP/SIP-NKE.kmodproj/sip_inet.c",
    "type": "EnumCase"
  },
  {
    "hex": "0x1",
    "name": "ipv4_stopping",
    "source": "SharedIP/SIP-NKE.kmodproj/sip_inet.c",
    "type": "EnumCase"
  },
  {
    "hex": "0x0",
    "name": "tcp_blue_owned",
    "source": "SharedIP/SIP-NKE.kmodproj/sip_inet.c",
    "type": "EnumCase"
  },
  {
    "hex": "0x0",
    "name": "udp_blue_owned",
    "source": "SharedIP/SIP-NKE.kmodproj/sip_inet.c",
    "type": "EnumCase"
  },
  {
    "hex": "0x0",
    "name": "ipv4_stopping",
    "source": "SharedIP/SIP-NKE.kmodproj/sip_inet.c",
    "type": "EnumCase"
  },
  {
    "hex": "0x0",
    "name": "owner",
    "source": "SharedIP/SIP-NKE.kmodproj/sip_inet.c",
    "type": "EnumCase"
  },
  {
    "hex": "0x0",
    "name": "s_addr",
    "source": "SharedIP/SIP-NKE.kmodproj/sip_inet.c",
    "type": "EnumCase"
  },
  {
    "hex": "0x0",
    "name": "fport",
    "source": "SharedIP/SIP-NKE.kmodproj/sip_inet.c",
    "type": "EnumCase"
  },
  {
    "hex": "0x0",
    "name": "s_addr",
    "source": "SharedIP/SIP-NKE.kmodproj/sip_inet.c",
    "type": "EnumCase"
  },
  {
    "hex": "0x0",
    "name": "fport",
    "source": "SharedIP/SIP-NKE.kmodproj/sip_inet.c",
    "type": "EnumCase"
  },
  {
    "hex": "0x0",
    "name": "ip_filter",
    "source": "SharedIP/SIP-NKE.kmodproj/sip_inet.c",
    "type": "EnumCase"
  }
]